LICENSE
MANIFEST.in
README.md
setup.py
vimtips/__init__.py
vimtips/__main__.py
vimtips/_version.py
vimtips/cli.py
vimtips/config.py
vimtips/gui.py
vimtips/tips.py
vimtips/unblank_daemon.py
vimtips/vimlogo.svg
vimtips.egg-info/PKG-INFO
vimtips.egg-info/SOURCES.txt
vimtips.egg-info/dependency_links.txt
vimtips.egg-info/entry_points.txt
vimtips.egg-info/requires.txt
vimtips.egg-info/top_level.txt
vimtips/sources/__init__.py
vimtips/sources/twitter.py
vimtips/unblank_check/Makefile
vimtips/unblank_check/__init__.py
vimtips/unblank_check/gnome-screensaver/__init__.py
vimtips/unblank_check/gnome-screensaver/unblank_check.sh
vimtips/unblank_check/macos_display_state/Makefile
vimtips/unblank_check/macos_display_state/__init__.py
vimtips/unblank_check/macos_display_state/unblank_check.c
vimtips/unblank_check/x11/Makefile
vimtips/unblank_check/x11/__init__.py
vimtips/unblank_check/x11/unblank_check.c
vimtips/unblank_check/xfce4-screensaver/__init__.py
vimtips/unblank_check/xfce4-screensaver/unblank_check.sh
vimtips/unblank_check/xscreensaver/__init__.py
vimtips/unblank_check/xscreensaver/unblank_check.sh